cfonb/__init__.py
cfonb/parser/__init__.py
cfonb/parser/common.py
cfonb/parser/statement.py
cfonb/tests/__init__.py
cfonb/tests/test_all.py
cfonb/tests/test_statement.py
cfonb/tests/test_transfert.py
cfonb/writer/__init__.py
cfonb/writer/common.py
cfonb/writer/statement.py
cfonb/writer/transfert.py
python_cfonb-2.13.dist-info/COPYING.LESSER
python_cfonb-2.13.dist-info/METADATA
python_cfonb-2.13.dist-info/WHEEL
python_cfonb-2.13.dist-info/top_level.txt
python_cfonb-2.13.dist-info/RECORD
