Metadata-Version: 2.1
Name: python-cfonb
Version: 2.13
Summary: Pure Python lib to read/write CFONB files, forked from https://github.com/akretion/python-cfonb
Home-page: https://github.com/dhatim/python-cfonb
Author: Dhatim
Author-email: contact@dhatim.com
License: LGPL
Keywords: cfonb,bank,statement,parser
Platform: UNKNOWN
Requires-Python: >=2.7
Requires-Dist: semantic-version (>=2.7.0)
Requires-Dist: toml
